yamlflow/__init__.py
yamlflow/cli/__init__.py
yamlflow/cli/commands/__init__.py
yamlflow/cli/commands/_build.py
yamlflow/cli/commands/_init.py
yamlflow/cli/commands/_publish.py
yamlflow/cli/commands/_run.py
yamlflow/cli/commands/_version.py
yamlflow/cli/constants.py
yamlflow/cli/manifest.py
yamlflow/dockerfiles/app/Dockerfile
yamlflow/dockerfiles/backend/sklearn-cpu/Dockerfile
yamlflow/dockerfiles/backend/torch-cpu/Dockerfile
yamlflow/dockerfiles/core/Dockerfile
yamlflow/dockerfiles/core/scripts/gunicorn_conf.py
yamlflow/dockerfiles/core/scripts/main.py
yamlflow/dockerfiles/core/scripts/start.sh
yamlflow-0.0.9.dist-info/entry_points.txt
yamlflow-0.0.9.dist-info/LICENSE
yamlflow-0.0.9.dist-info/WHEEL
yamlflow-0.0.9.dist-info/METADATA
yamlflow-0.0.9.dist-info/RECORD
