Metadata-Version: 2.1
Name: yamlflow
Version: 0.0.9
Summary: Yet Another ML flow
Home-page: https://github.com/sevakharutyunyan/yamlflow
Author: Sevak Harutyunyan
Author-email: sevak.g.harutyunyan@gmail.com
Requires-Python: >=3.7,<4.0
Classifier: Operating System :: OS Independent
Classifier: Programming Language :: Python :: 3
Classifier: Programming Language :: Python :: 3.7
Classifier: Programming Language :: Python :: 3.8
Classifier: Programming Language :: Python :: 3.9
Requires-Dist: click (>=7.0.0,<8.0.0)
Requires-Dist: docker (>=5.0.0,<6.0.0)
Requires-Dist: pyyaml (>=5.4.1,<6.0.0)
Project-URL: Repository, https://github.com/sevakharutyunyan/yamlflow
